[
  {
    "type": "paragraph",
    "children": [
      {
        "text": "Magna est pariatur minim mollit. Ex ipsum sit qui elit. Eiusmod incididunt excepteur aute culpa irure anim et. Eu id consequat eu magna minim do ipsum enim incididunt dolor incididunt deserunt. Mollit ipsum qui in mollit ut esse ea minim pariatur."
      }
    ]
  },
  {
    "type": "paragraph",
    "children": [
      {
        "text": "\n"
      }
    ]
  },
  {
    "type": "paragraph",
    "children": [
      {
        "text": "Do"
      }
    ]
  }
]