[
  {
    "type": "paragraph",
    "children": [
      {
        "text": "Enim sint enim deserunt eu. Do consequat nostrud do voluptate esse ad in aute cillum. Proident excepteur aute laboris esse tempor do. Labore est anim cupidatat exercitation fugiat aliqua laborum ut deserunt."
      }
    ]
  },
  {
    "type": "paragraph",
    "children": [
      {
        "text": "\n"
      }
    ]
  },
  {
    "type": "paragraph",
    "children": [
      {
        "text": "Non sunt non in excepteur nostrud id sit. "
      }
    ]
  }
]